setuptools_betterproto/__init__.py
setuptools_betterproto/_command.py
setuptools_betterproto/_config.py
setuptools_betterproto/_install.py
setuptools_betterproto/conftest.py
setuptools_betterproto/py.typed
setuptools_betterproto-0.3.0.dist-info/LICENSE
setuptools_betterproto-0.3.0.dist-info/METADATA
setuptools_betterproto-0.3.0.dist-info/WHEEL
setuptools_betterproto-0.3.0.dist-info/entry_points.txt
setuptools_betterproto-0.3.0.dist-info/top_level.txt
setuptools_betterproto-0.3.0.dist-info/RECORD
